pytreelog/README.md
pytreelog/__init__.py
pytreelog/pytreelog.py
pytreelog-194rc0.post1.dist-info/LICENSE
pytreelog-194rc0.post1.dist-info/METADATA
pytreelog-194rc0.post1.dist-info/WHEEL
pytreelog-194rc0.post1.dist-info/top_level.txt
pytreelog-194rc0.post1.dist-info/RECORD
