Metadata-Version: 2.1
Name: pytreelog
Version: 194rc0.post1
Summary: Tree-like logging util for python
Home-page: https://gitlab.com/runsun/pytreelog
Author: runsun
Author-email: runsun@gmail.com
License: UNKNOWN
Platform: UNKNOWN
Classifier: Programming Language :: Python :: 3
Classifier: License :: OSI Approved :: MIT License
Classifier: Operating System :: OS Independent
